{
  "type": "degeneracycraft:basic_technology_machine_part_processor_recipe",
  "energy": 1000.0,
  "time": 10.0,
  "input0": {
    "item": "degeneracycraft:iron_rod"
  },
  "input1": {
    "item": "degeneracycraft:copper_plate"
  },
  "input2": {
    "item": "degeneracycraft:iron_rod"
  },
  "input3": {
    "item": "degeneracycraft:iron_plate"
  },
  "input4": {
    "item": "degeneracycraft:iron_bearing"
  },
  "input5": {
    "item": "degeneracycraft:iron_plate"
  },
  "input6": {
    "item": "degeneracycraft:iron_rod"
  },
  "input7": {
    "item": "degeneracycraft:copper_plate"
  },
  "input8": {
    "item": "degeneracycraft:iron_rod"
  },
  "output0": {
    "item": "degeneracycraft:basic_turbine"
  }
}